deviceID/__init__.py
deviceID/deviceID.py
deviceID-0.1.0.dist-info/METADATA
deviceID-0.1.0.dist-info/WHEEL
deviceID-0.1.0.dist-info/top_level.txt
deviceID-0.1.0.dist-info/RECORD
