Metadata-Version: 2.1
Name: deviceID
Version: 0.1.0
Summary: deviceID python client
Home-page: UNKNOWN
Author: deviceID
License: MIT
Platform: UNKNOWN
